catapa/__init__.py
catapa/auto_refresh_api_client.py
catapa/wrapper.py
catapa/auth/catapa_auth.py
catapa/auth/constant.py
openapi_client/__init__.py
openapi_client/api_client.py
openapi_client/api_response.py
openapi_client/configuration.py
openapi_client/exceptions.py
openapi_client/py.typed
openapi_client/rest.py
openapi_client/api/__init__.py
openapi_client/api/analytics_api.py
openapi_client/api/anomaly_detection_api.py
openapi_client/api/bank_account_configuration_api.py
openapi_client/api/bpjs_healthcare_api.py
openapi_client/api/bpjs_manpower_api.py
openapi_client/api/company_bank_account_api.py
openapi_client/api/contact_information_api.py
openapi_client/api/custom_table_api.py
openapi_client/api/custom_table_entry_api.py
openapi_client/api/editable_salary_preprocess_api.py
openapi_client/api/employee_api.py
openapi_client/api/employee_bank_account_configuration_api.py
openapi_client/api/employee_bpjs_membership_api.py
openapi_client/api/employee_detail_api.py
openapi_client/api/employee_paygroup_api.py
openapi_client/api/employee_payment_item_group_sequence_api.py
openapi_client/api/employee_salary_template_api.py
openapi_client/api/employee_variable_api.py
openapi_client/api/employment_status_api.py
openapi_client/api/families_api.py
openapi_client/api/former_employee_income_api.py
openapi_client/api/identity_cards_api.py
openapi_client/api/master_data_api.py
openapi_client/api/oauth_client_api.py
openapi_client/api/organization_api.py
openapi_client/api/paygroup_api.py
openapi_client/api/payroll_others_api.py
openapi_client/api/payroll_process_snapshot_api.py
openapi_client/api/payslip_api.py
openapi_client/api/role_api.py
openapi_client/api/salary_calculation_api.py
openapi_client/api/salary_item_api.py
openapi_client/api/salary_payment_api.py
openapi_client/api/salary_template_api.py
openapi_client/api/severance_api.py
openapi_client/api/tax_api.py
openapi_client/api/tax_membership_api.py
openapi_client/api/tax_membership_history_api.py
catapa-0.1.4.dist-info/METADATA
catapa-0.1.4.dist-info/WHEEL
catapa-0.1.4.dist-info/top_level.txt
catapa-0.1.4.dist-info/RECORD
