Metadata-Version: 2.4
Name: catapa
Version: 0.1.4
Summary: Python client library for Catapa API
Author-email: Catapa Team <dev@catapa.com>
Project-URL: Homepage, https://github.com/GDP-ADMIN/CATAPA-API
Project-URL: Documentation, https://api-docs.catapa.com/
Project-URL: Repository, https://github.com/GDP-ADMIN/CATAPA-API
Keywords: catapa,api,client,hr,payroll
Classifier: Development Status :: 4 - Beta
Classifier: Intended Audience :: Developers
Classifier: License :: OSI Approved :: MIT License
Classifier: Programming Language :: Python :: 3
Classifier: Programming Language :: Python :: 3.11
Classifier: Programming Language :: Python :: 3.12
Classifier: Programming Language :: Python :: 3.13
Requires-Python: >=3.11
Requires-Dist: urllib3>=1.25.3
Requires-Dist: python-dateutil
Requires-Dist: pydantic>=2.0.0
Requires-Dist: typing-extensions>=4.7.1
Requires-Dist: requests>=2.32.0
Requires-Dist: flake8<7.3.0
Provides-Extra: dev
Requires-Dist: pytest>=7.0.0; extra == "dev"
Requires-Dist: pytest-cov; extra == "dev"
Requires-Dist: coverage>=7.0.0; extra == "dev"
Requires-Dist: pre-commit>=4.2.0; extra == "dev"
Requires-Dist: ruff>=0.14.0; extra == "dev"
Requires-Dist: mypy>=1.0.0; extra == "dev"
